MANIFEST.in
setup.cfg
setup.py
docs/HISTORY.txt
docs/LICENSE.txt
docs/USE.txt
etl/__init__.py
etl/etllib.py
etl/poster.py
etl/repackage.py
etl/repackageandpost.py
etl/similarity.py
etl/translatejson.py
etl/tsvtojson.py
etllib.egg-info/PKG-INFO
etllib.egg-info/SOURCES.txt
etllib.egg-info/dependency_links.txt
etllib.egg-info/entry_points.txt
etllib.egg-info/requires.txt
etllib.egg-info/top_level.txt
etllib.egg-info/zip-safe