Metadata-Version: 1.1
Name: etllib
Version: 1.1
Summary: Extract, Transform and Load library.
Home-page: http://github.com/chrismattmann/etllib
Author: Chris Mattmann
Author-email: chris.a.mttmnn@nasa.gov
License: 
